torchdrivesim/__init__.py
torchdrivesim/_iou_utils.py
torchdrivesim/goals.py
torchdrivesim/infractions.py
torchdrivesim/kinematic.py
torchdrivesim/lanelet2.py
torchdrivesim/map.py
torchdrivesim/mesh.py
torchdrivesim/simulator.py
torchdrivesim/traffic_controls.py
torchdrivesim/traffic_lights.py
torchdrivesim/utils.py
torchdrivesim/behavior/__init__.py
torchdrivesim/behavior/common.py
torchdrivesim/behavior/heuristic.py
torchdrivesim/behavior/iai.py
torchdrivesim/behavior/replay.py
torchdrivesim/rendering/__init__.py
torchdrivesim/rendering/base.py
torchdrivesim/rendering/cv2.py
torchdrivesim/rendering/nvdiffrast.py
torchdrivesim/rendering/pytorch3d.py
torchdrivesim/resources/maps/carla_Town01/carla_Town01.osm
torchdrivesim/resources/maps/carla_Town01/carla_Town01_mesh.json
torchdrivesim/resources/maps/carla_Town01/carla_Town01_stoplines.json
torchdrivesim/resources/maps/carla_Town01/carla_Town01_traffic_light_controller.json
torchdrivesim/resources/maps/carla_Town01/metadata.json
torchdrivesim/resources/maps/carla_Town02/carla_Town02.osm
torchdrivesim/resources/maps/carla_Town02/carla_Town02_mesh.json
torchdrivesim/resources/maps/carla_Town02/carla_Town02_stoplines.json
torchdrivesim/resources/maps/carla_Town02/carla_Town02_traffic_light_controller.json
torchdrivesim/resources/maps/carla_Town02/metadata.json
torchdrivesim/resources/maps/carla_Town03/carla_Town03.osm
torchdrivesim/resources/maps/carla_Town03/carla_Town03_mesh.json
torchdrivesim/resources/maps/carla_Town03/carla_Town03_stoplines.json
torchdrivesim/resources/maps/carla_Town03/carla_Town03_traffic_light_controller.json
torchdrivesim/resources/maps/carla_Town03/metadata.json
torchdrivesim/resources/maps/carla_Town04/carla_Town04.osm
torchdrivesim/resources/maps/carla_Town04/carla_Town04_mesh.json
torchdrivesim/resources/maps/carla_Town04/carla_Town04_stoplines.json
torchdrivesim/resources/maps/carla_Town04/carla_Town04_traffic_light_controller.json
torchdrivesim/resources/maps/carla_Town04/metadata.json
torchdrivesim-0.2.3.dist-info/LICENSE.md
torchdrivesim-0.2.3.dist-info/METADATA
torchdrivesim-0.2.3.dist-info/WHEEL
torchdrivesim-0.2.3.dist-info/top_level.txt
torchdrivesim-0.2.3.dist-info/RECORD
