Metadata-Version: 2.1
Name: torchdrivesim
Version: 0.2.3
Summary: TorchDriveSim is a lightweight 2D driving simulator, built entirely in PyTorch, primarily intended as a training environment for developing autonomous driving algorithms
Author-email: "Inverted AI Ltd." <info@inverted.ai>
License: Apache License
Keywords: torch,drive,sim,torch-drive-sim,torchdrivesim,invertedai,inverted ai
Classifier: Programming Language :: Python :: 3
Requires-Python: >=3.8
License-File: LICENSE.md
Requires-Dist: pandas
Requires-Dist: numpy
Requires-Dist: shapely
Requires-Dist: scipy
Requires-Dist: imageio
Requires-Dist: torch >=1.10.1
Requires-Dist: invertedai
Requires-Dist: omegaconf
Requires-Dist: opencv-python
Provides-Extra: dev
Requires-Dist: gym ; extra == 'dev'
Provides-Extra: docs
Requires-Dist: Sphinx ; extra == 'docs'
Requires-Dist: myst-parser ; extra == 'docs'
Requires-Dist: furo ; extra == 'docs'
Requires-Dist: sphinx-copybutton ; extra == 'docs'
Requires-Dist: sphinx-design ; extra == 'docs'
Requires-Dist: sphinxcontrib-applehelp ; extra == 'docs'
Requires-Dist: sphinxcontrib-devhelp ; extra == 'docs'
Requires-Dist: sphinxcontrib-htmlhelp ; extra == 'docs'
Requires-Dist: sphinxcontrib-jsmath ; extra == 'docs'
Requires-Dist: sphinxcontrib-qthelp ; extra == 'docs'
Requires-Dist: sphinxcontrib-serializinghtml ; extra == 'docs'
Requires-Dist: sphinx-autoapi ; extra == 'docs'
Requires-Dist: pydata-sphinx-theme ; extra == 'docs'
Requires-Dist: sphinx-autobuild ; extra == 'docs'
Requires-Dist: nbsphinx ; extra == 'docs'
Requires-Dist: breathe ; extra == 'docs'
Provides-Extra: tests
Requires-Dist: pytest ==5.4.3 ; extra == 'tests'
